xicam/plugins/DataHandlerPlugin.py
xicam/plugins/DataResourcePlugin.py
xicam/plugins/EZPlugin.py
xicam/plugins/FittableModelPlugin.py
xicam/plugins/GUIPlugin.py
xicam/plugins/ProcessingPlugin.py
xicam/plugins/SettingsPlugin.py
xicam/plugins/WidgetPlugin.py
xicam/plugins/__init__.py
xicam/plugins/_version.py
xicam/plugins/cammart.py
xicam/plugins/venvs.py
xicam.plugins-2.1.6.dist-info/METADATA
xicam.plugins-2.1.6.dist-info/RECORD
xicam.plugins-2.1.6.dist-info/WHEEL
xicam.plugins-2.1.6.dist-info/top_level.txt
