Metadata-Version: 2.1
Name: xicam.plugins
Version: 2.1.6
Summary: The CAMERA platform for synchrotron data management, visualization, and reduction. The xicam.gui package contains all gui code of the Xi-cam platform, as part of the xicam namespace package. For the backend components, see "xicam.core".
Home-page: https://github.com/ronpandolfi/Xi-cam
Author: Ronald J Pandolfi
Author-email: ronpandolfi@lbl.gov
License: BSD
Keywords: synchrotron analysis x-ray scattering tomography
Platform: UNKNOWN
Classifier: Development Status :: 3 - Alpha
Classifier: Intended Audience :: Science/Research
Classifier: Topic :: Scientific/Engineering :: Physics
Classifier: License :: OSI Approved :: BSD License
Classifier: Programming Language :: Python :: 3.6
Provides-Extra: tests
Requires-Dist: yapsy
Requires-Dist: astropy
Requires-Dist: signalslot
Requires-Dist: virtualenv
Requires-Dist: requests
Requires-Dist: appdirs
Requires-Dist: fabio
Provides-Extra: tests
Requires-Dist: pytest; extra == 'tests'
Requires-Dist: coverage; extra == 'tests'
